hardverapro_mcp/__init__.py
hardverapro_mcp/cli.py
scraper/__init__.py
scraper/scraper.py
hardverapro_mcp-0.2.5.dist-info/METADATA
hardverapro_mcp-0.2.5.dist-info/WHEEL
hardverapro_mcp-0.2.5.dist-info/entry_points.txt
hardverapro_mcp-0.2.5.dist-info/top_level.txt
hardverapro_mcp-0.2.5.dist-info/RECORD
