Metadata-Version: 2.4
Name: hardverapro-mcp
Version: 0.2.5
Summary: Add your description here
Requires-Python: >=3.13
Requires-Dist: beautifulsoup4>=4.13.4
Requires-Dist: mcp[cli]>=0.0.1
Requires-Dist: requests>=2.32.4
